agda_kernel/__init__.py
agda_kernel/__main__.py
agda_kernel/install.py
agda_kernel/kernel.py
agda_kernel-0.64.dist-info/LICENSE
agda_kernel-0.64.dist-info/METADATA
agda_kernel-0.64.dist-info/WHEEL
agda_kernel-0.64.dist-info/top_level.txt
agda_kernel-0.64.dist-info/RECORD
