Metadata-Version: 2.1
Name: agda-kernel
Version: 0.64
Summary: A rudimentary Jupyter kernel for Agda
Home-page: https://github.com/lclem/agda-kernel
Author: Lorenzo Clemente
Author-email: clementelorenzo@gmail.com
License: UNKNOWN
Platform: UNKNOWN
Classifier: Intended Audience :: Developers
Classifier: License :: OSI Approved :: BSD License
Classifier: Programming Language :: Python :: 3
